README.md
setup.py
kpar/__init__.py
kpar/core.py
kpar/units.py
kpar.egg-info/PKG-INFO
kpar.egg-info/SOURCES.txt
kpar.egg-info/dependency_links.txt
kpar.egg-info/entry_points.txt
kpar.egg-info/not-zip-safe
kpar.egg-info/requires.txt
kpar.egg-info/top_level.txt